nasdaqprophet/__init__.py
nasdaqprophet/nasdaqprophet.py
nasdaqprophet-0.0.3.dist-info/METADATA
nasdaqprophet-0.0.3.dist-info/WHEEL
nasdaqprophet-0.0.3.dist-info/top_level.txt
nasdaqprophet-0.0.3.dist-info/RECORD
